streamlit_job_scheduler/__init__.py
streamlit_job_scheduler/enums.py
streamlit_job_scheduler/models.py
streamlit_job_scheduler/scheduler.py
streamlit_job_scheduler/ui.py
streamlit_job_scheduler-0.0.1.dist-info/licenses/AUTHORS.md
streamlit_job_scheduler-0.0.1.dist-info/licenses/LICENSE
tests/__init__.py
tests/test_scheduler.py
tests/test_ui.py
streamlit_job_scheduler-0.0.1.dist-info/METADATA
streamlit_job_scheduler-0.0.1.dist-info/WHEEL
streamlit_job_scheduler-0.0.1.dist-info/top_level.txt
streamlit_job_scheduler-0.0.1.dist-info/RECORD
