Metadata-Version: 2.4
Name: streamlit-job-scheduler
Version: 0.0.1
Summary: A Streamlit-based job scheduler with one-time and cron scheduling support
Author: Chandra D P
Author-email: Chandra D P <chandrasuvarna102@gmail.com>
License-Expression: MIT
Project-URL: Homepage, https://github.com/CHANDRADP/streamlit-job-scheduler
Project-URL: Issues, https://github.com/CHANDRADP/streamlit-job-scheduler/issues
Keywords: streamlit,scheduler,cron,ui
Platform: any
Classifier: Development Status :: 5 - Production/Stable
Classifier: Programming Language :: Python :: 3
Classifier: Operating System :: OS Independent
Requires-Python: >=3.8
License-File: LICENSE
License-File: AUTHORS.md
Requires-Dist: streamlit>=1.25.0
Provides-Extra: dev
Requires-Dist: pytest>=7.0.0; extra == "dev"
Dynamic: license-file
